a2anet_mcp/__about__.py
a2anet_mcp/__init__.py
a2anet_mcp/__main__.py
a2anet_mcp/server.py
a2anet_mcp/core/__init__.py
a2anet_mcp/core/agents.py
a2anet_mcp/core/config.py
a2anet_mcp/core/conversation.py
a2anet_mcp/core/types.py
a2anet_mcp/storage/__init__.py
a2anet_mcp/storage/paths.py
a2anet_mcp/storage/persistence.py
a2anet_mcp/tools/__init__.py
a2anet_mcp/tools/artifacts.py
a2anet_mcp/tools/discovery.py
a2anet_mcp/tools/messaging.py
a2anet_mcp/tools/utils.py
a2anet_mcp-1.0.3.dist-info/METADATA
a2anet_mcp-1.0.3.dist-info/WHEEL
a2anet_mcp-1.0.3.dist-info/entry_points.txt
a2anet_mcp-1.0.3.dist-info/licenses/LICENSE
a2anet_mcp-1.0.3.dist-info/RECORD
