Metadata-Version: 2.4
Name: a2anet-mcp
Version: 1.0.3
Summary: An MCP server for the Agent2Agent (A2A) protocol
Project-URL: Documentation, https://github.com/A2ANet/a2a-mcp#readme
Project-URL: Issues, https://github.com/A2ANet/a2a-mcp/issues
Project-URL: Source, https://github.com/A2ANet/a2a-mcp
Author-email: A2A Net <hello@a2anet.com>
License-Expression: Apache-2.0
License-File: LICENSE
Keywords: a2a,a2anet,agent,agent2agent,ai,llm,mcp,multi-agent
Classifier: Development Status :: 4 - Beta
Classifier: Programming Language :: Python
Classifier: Programming Language :: Python :: 3.13
Classifier: Programming Language :: Python :: Implementation :: CPython
Classifier: Programming Language :: Python :: Implementation :: PyPy
Requires-Python: >=3.13
Requires-Dist: a2a-sdk>=0.3.21
Requires-Dist: loguru>=0.7.3
Requires-Dist: mcp>=1.2.0
Requires-Dist: platformdirs>=4.0.0
